{
  "version": "1",
  "cognitoConfig": {
    "identityPoolName": "frontendd70d18e5_identitypool_d70d18e5",
    "allowUnauthenticatedIdentities": false,
    "resourceNameTruncated": "fronted70d18e5",
    "userPoolName": "frontendd70d18e5_userpool_d70d18e5",
    "autoVerifiedAttributes": [
      "email"
    ],
    "mfaConfiguration": "OFF",
    "mfaTypes": [
      "SMS Text Message"
    ],
    "smsAuthenticationMessage": "Your authentication code is {####}",
    "smsVerificationMessage": "Your verification code is {####}",
    "emailVerificationSubject": "Your verification code",
    "emailVerificationMessage": "Your verification code is {####}",
    "defaultPasswordPolicy": false,
    "passwordPolicyMinLength": 8,
    "passwordPolicyCharacters": [],
    "requiredAttributes": [
      "email"
    ],
    "aliasAttributes": [],
    "userpoolClientGenerateSecret": false,
    "userpoolClientRefreshTokenValidity": 30,
    "userpoolClientWriteAttributes": [
      "email"
    ],
    "userpoolClientReadAttributes": [
      "email"
    ],
    "userpoolClientLambdaRole": "fronted70d18e5_userpoolclient_lambda_role",
    "userpoolClientSetAttributes": false,
    "sharedId": "d70d18e5",
    "resourceName": "frontendd70d18e5",
    "authSelections": "identityPoolAndUserPool",
    "useDefault": "defaultSocial",
    "hostedUI": true,
    "usernameAttributes": [
      "email"
    ],
    "hostedUIDomainName": "frontendd70d18e5-d70d18e5",
    "authProvidersUserPool": [],
    "hostedUIProviderMeta": "[]",
    "oAuthMetadata": "{\"AllowedOAuthFlows\":[\"code\"],\"AllowedOAuthScopes\":[\"phone\",\"email\",\"openid\",\"profile\",\"aws.cognito.signin.user.admin\"],\"CallbackURLs\":[\"http://localhost:3000/\"],\"LogoutURLs\":[\"http://localhost:3000/\"]}",
    "userPoolGroupList": [],
    "serviceName": "Cognito",
    "usernameCaseSensitive": false,
    "useEnabledMfas": true
  }
}